pyzf/__init__.py
pyzf/interfaces.py
pyzf/interfaces_test.py
pyzf/version.py
pyzf-1.0.2.dist-info/LICENSE
pyzf-1.0.2.dist-info/METADATA
pyzf-1.0.2.dist-info/WHEEL
pyzf-1.0.2.dist-info/top_level.txt
pyzf-1.0.2.dist-info/RECORD
